circle_schema/__init__.py
circle_schema/py.typed
circle_schema/v0_10/__init__.py
circle_schema/v0_10/circle/ATan2Options.py
circle_schema/v0_10/circle/AbsOptions.py
circle_schema/v0_10/circle/ActivationFunctionType.py
circle_schema/v0_10/circle/AddNOptions.py
circle_schema/v0_10/circle/AddOptions.py
circle_schema/v0_10/circle/ArgMaxOptions.py
circle_schema/v0_10/circle/ArgMinOptions.py
circle_schema/v0_10/circle/AssignVariableOptions.py
circle_schema/v0_10/circle/BCQFullyConnectedOptions.py
circle_schema/v0_10/circle/BCQGatherOptions.py
circle_schema/v0_10/circle/BatchMatMulOptions.py
circle_schema/v0_10/circle/BatchToSpaceNDOptions.py
circle_schema/v0_10/circle/BidirectionalSequenceLSTMOptions.py
circle_schema/v0_10/circle/BidirectionalSequenceRNNOptions.py
circle_schema/v0_10/circle/BitcastOptions.py
circle_schema/v0_10/circle/BitwiseXorOptions.py
circle_schema/v0_10/circle/BroadcastToOptions.py
circle_schema/v0_10/circle/BucketizeOptions.py
circle_schema/v0_10/circle/Buffer.py
circle_schema/v0_10/circle/BuiltinOperator.py
circle_schema/v0_10/circle/BuiltinOptions.py
circle_schema/v0_10/circle/BuiltinOptions2.py
circle_schema/v0_10/circle/CallOnceOptions.py
circle_schema/v0_10/circle/CallOptions.py
circle_schema/v0_10/circle/CastOptions.py
circle_schema/v0_10/circle/CombinerType.py
circle_schema/v0_10/circle/CompressionType.py
circle_schema/v0_10/circle/ConcatEmbeddingsOptions.py
circle_schema/v0_10/circle/ConcatenationOptions.py
circle_schema/v0_10/circle/Conv2DOptions.py
circle_schema/v0_10/circle/Conv3DOptions.py
circle_schema/v0_10/circle/CosOptions.py
circle_schema/v0_10/circle/CumsumOptions.py
circle_schema/v0_10/circle/CustomOptionsFormat.py
circle_schema/v0_10/circle/CustomQuantization.py
circle_schema/v0_10/circle/DataFormat.py
circle_schema/v0_10/circle/DensifyOptions.py
circle_schema/v0_10/circle/DepthToSpaceOptions.py
circle_schema/v0_10/circle/DepthwiseConv2DOptions.py
circle_schema/v0_10/circle/DequantizeOptions.py
circle_schema-0.10.0.dist-info/LICENSE
circle_schema-0.10.0.dist-info/METADATA
circle_schema-0.10.0.dist-info/WHEEL
circle_schema-0.10.0.dist-info/top_level.txt
circle_schema-0.10.0.dist-info/RECORD
